CHANGES.txt
LICENSE.txt
MANIFEST.in
README.rst
requirements.txt
setup.py
mmpy.egg-info/PKG-INFO
mmpy.egg-info/SOURCES.txt
mmpy.egg-info/dependency_links.txt
mmpy.egg-info/requires.txt
mmpy.egg-info/top_level.txt
src/__init__.py
src/artist.py
src/chart.py
src/entity.py
src/list.py
src/releasegroup.py