Metadata-Version: 1.1
Name: mmpy
Version: 0.1.5
Summary: Musicmetric API Wrapper
Home-page: https://github.com/musicmetric/mmpy
Author: Ben Fields
Author-email: ben@musicmetric.com
License: ISCL
Platform: UNKNOWN
Classifier: Development Status :: 3 - Alpha
Classifier: License :: OSI Approved :: ISC License (ISCL)
Classifier: Intended Audience :: Developers
Classifier: Operating System :: OS Independent
Provides: mmpy
